ydl/__init__.py
ydl/ydl.py
Ydl-1.3.0.dist-info/METADATA
Ydl-1.3.0.dist-info/WHEEL
Ydl-1.3.0.dist-info/top_level.txt
Ydl-1.3.0.dist-info/RECORD
