Metadata-Version: 2.1
Name: Ydl
Version: 1.3.0
Summary: wrapper of YouTube-dl
Home-page: UNKNOWN
Author: Kerodon
License: UNKNOWN
Platform: UNKNOWN
